midi_psychopy/__init__.py
midi_psychopy/functions.py
midi_psychopy/midi_controller.py
midi_psychopy/midi_interface.py
midi_psychopy-0.0.1.dist-info/LICENSE
midi_psychopy-0.0.1.dist-info/METADATA
midi_psychopy-0.0.1.dist-info/WHEEL
midi_psychopy-0.0.1.dist-info/top_level.txt
midi_psychopy-0.0.1.dist-info/RECORD
