Metadata-Version: 2.1
Name: midi-psychopy
Version: 0.0.1
Summary: A Python interface for asynchronous MIDI data collection using PsychoPy
Home-page: https://github.com/xywang01/midi-psychopy
Author: X. Michael Wang, Centre for Motor Control, University of Toronto, Faculty of Kinesiology and Physical Education
Author-email: michaelwxy.wang@utoronto.ca
License: MIT
Download-URL: https://github.com/xywang01/midi-psychopy/archive/refs/tags/0.0.1.tar.gz
Platform: UNKNOWN
License-File: LICENSE
Requires-Dist: mido
Requires-Dist: numpy
Requires-Dist: pandas
Requires-Dist: matplotlib
